{
  "hash": "b619ba8d7a25252e5dbb37e5e5a09cad",
  "result": {
    "markdown": "# Introduction {#sec-introfichespratiques}\n\n\n\n\n::: {.cell}\n\n```{.r .cell-code}\nlibrary(rtauargus)\nlibrary(dplyr)\n```\n:::\n\n\nCes fiches pratiques ont été réalisées avec la version 1.2.0 de\n`rtauargus` et la version 4.2.3 de `TauArgus`.\n\n## Structure des données\n\nTous les tableaux fournis en entrée de `rtauargus` ont une structure\nidentique :\n\n-   Les variables décrivant les croisements (variables catégorielles)\n    sont placées au début\n-   `FREQ` la variable indiquant le nombre d'unités statistiques\n    contribuant à la cellule;\n-   `VALUE` la variable indiquant la somme pondérée des valeurs de\n    l'ensemble des contributeurs à la cellule (ex : un chiffre\n    d'affaires, un nombre de personnes en emploi au 31/12, etc.);\n-   `MAX` la valeur du plus gros contributeur à la cellule.\n\nN.B : pour les tableaux de fréquence `FREQ` = `VALUE`.\n\n",
    "supporting": [],
    "filters": [
      "rmarkdown/pagebreak.lua"
    ],
    "includes": {},
    "engineDependencies": {},
    "preserve": {},
    "postProcess": true
  }
}